ezprof/__init__.py
ezprof-0.0.1.dist-info/METADATA
ezprof-0.0.1.dist-info/WHEEL
ezprof-0.0.1.dist-info/top_level.txt
ezprof-0.0.1.dist-info/RECORD
